E200/__init__.py
E200/classes.py
E200/E200_api_getdat.py
E200/E200_api_getUID.py
E200/E200_api_updateUID.py
E200/E200_create_data.py
E200/E200_Dat.py
E200/E200_dataset2str.py
E200/E200_Image_Iter.py
E200/E200_load_data.py
E200/E200_load_data_gui.py
E200/E200_load_images.py
E200/eaxis.py
E200/eaxis_class.py
E200/get_matlab.py
E200/get_remoteprefix.py
E200/get_valid_filename.py
E200/setQS.py
E200/matlab/convert_mat_file.m
E200-1.3.4.dist-info/DESCRIPTION.rst
E200-1.3.4.dist-info/METADATA
E200-1.3.4.dist-info/metadata.json
E200-1.3.4.dist-info/RECORD
E200-1.3.4.dist-info/top_level.txt
E200-1.3.4.dist-info/WHEEL
