Metadata-Version: 2.0
Name: E200
Version: 1.3.4
Summary: Datatype specification and loading package
Home-page: https://github.com/joelfrederico/E200
Author: Joel Frederico, SLAC National Accelerator Laboratory
Author-email: joelfred@slac.stanford.edu
License: MIT
Keywords: linac linear accelerator beam physics data datatype E200
Platform: UNKNOWN
Classifier: Development Status :: 5 - Production/Stable
Classifier: Intended Audience :: Science/Research
Classifier: Topic :: Scientific/Engineering :: Information Analysis
Classifier: License :: OSI Approved :: MIT License
Classifier: Programming Language :: Python :: 3
Classifier: Programming Language :: Python :: 3.4
Classifier: Programming Language :: Python :: 3 :: Only
Requires-Dist: Pillow (>=2.8.1)
Requires-Dist: SciSalt (>=1.1.0)
Requires-Dist: h5py
Requires-Dist: numpy
Requires-Dist: scipy
